docs/conf.py
grip/__init__.py
grip/agent/__init__.py
grip/agent/base_agent.py
grip/agent/demo_agent.py
grip/app/__init__.py
grip/app/app_interface.py
grip/environments/__init__.py
grip/environments/base_env.py
grip/environments/domain_randomiser.py
grip/environments/pick_and_place_env.py
grip/environments/reward.py
grip/environments/template_env.py
grip/io/__init__.py
grip/io/logging_utils.py
grip/io/timer.py
grip/io/tools.py
grip/math/__init__.py
grip/math/linalg.py
grip/math/quaternion.py
grip/math/transform.py
grip/motion/__init__.py
grip/motion/minjerk.py
grip/motion/path.py
grip/motion/pybullet_planner.py
grip/perception/__init__.py
grip/perception/image_utils.py
grip/perception/rgbd2pcd.py
grip/perception/tsdf_volume.py
grip/robot/__init__.py
grip/robot/articulated_object.py
grip/robot/bullet_robot.py
grip/robot/bullet_robotiq_2f_gripper.py
grip/robot/collision.py
grip/robot/end_effector_registry.py
grip/robot/entity.py
grip/robot/gripper_interface.py
grip/robot/gui.py
grip/robot/object.py
grip/robot/panda_gripper.py
grip/robot/panda_robot.py
grip/robot/robot_arm.py
grip/robot/robot_interface.py
grip/robot/types.py
grip/robot/world.py
grip/ros/__init__.py
grip/ros/depth_proc_launch.py
grip/ros/io.py
grip/ros/joint_state_tools.py
grip/ros/pc_conversions.py
grip/ros/ros2_future.py
grip/ros/ros_camera.py
grip/ros/ros_robot_arm.py
grip/ros/tf_tools.py
grip/ros/trajectory_action_client.py
grip/ros/trajectory_action_server.py
grip/ros/urdf_utils.py
grip/sensors/__init__.py
grip/sensors/camera.py
grip/sensors/sensor.py
grip_assets/__init__.py
grip_assets/config/sensors3d.yaml
grip_assets/media/basic_demo_2x.gif
grip_assets/media/moveit_demo.gif
grip_assets/media/simple_demo.gif
grip_assets/texture/dtd_crystalline_0217.jpg
grip_assets/texture/dtd_dotted_0114.jpg
grip_assets/texture/dtd_gauzy_0160.jpg
grip_assets/urdf/robots/panda.urdf.xacro
grip_assets/urdf/sample_objects/drinks_can/collision_simple_vhacd.obj
gripx-0.0.19.dist-info/licenses/LICENSE
gripx-0.0.19.dist-info/METADATA
gripx-0.0.19.dist-info/WHEEL
gripx-0.0.19.dist-info/top_level.txt
gripx-0.0.19.dist-info/RECORD
