Metadata-Version: 2.4
Name: gripx
Version: 0.0.19
Summary: Grip is a prototyping toolbox for manipulation research.
Home-page: https://github.com/eaa3/grip.git
Author: Ermano Arruda
Author-email: Ermano Arruda <ermano.arruda@gmail.com>
Maintainer: Ermano Arruda
Maintainer-email: ermano.arruda@gmail.com
Requires-Python: >=3.10,<3.13
License-File: LICENSE
Requires-Dist: setuptools>=69.0.0
Requires-Dist: numpy>=1.26.4
Requires-Dist: scipy>=1.11.1
Requires-Dist: pybullet>=3.2.6
Requires-Dist: open3d>=0.17.0
Requires-Dist: opencv-python>=4.10.0.84
Requires-Dist: matplotlib>=3.3.4
Requires-Dist: pybullet-planning-eaa
Requires-Dist: trimesh>=3.9.20
Requires-Dist: xatlas>=0.0.7
Requires-Dist: transforms3d>=0.4.1
Requires-Dist: strenum
Requires-Dist: ipython>=8.37.0
Provides-Extra: dev
Requires-Dist: pytest; extra == "dev"
Requires-Dist: ipdb; extra == "dev"
Requires-Dist: black>=25.1.0; extra == "dev"
Requires-Dist: check-manifest<=0.49,>=0.49; extra == "dev"
Requires-Dist: pre-commit<=3.3.3,>=3.3.3; extra == "dev"
Requires-Dist: pylint<=2.17.5,>=2.16; extra == "dev"
Requires-Dist: pytest-cov<=4.1,>=4.1; extra == "dev"
Requires-Dist: pytest-mock<=3.11.1,>=3.10; extra == "dev"
Requires-Dist: pytest-runner<=6.0,>=6.0; extra == "dev"
Requires-Dist: pytest<=7.4,>=7.4; extra == "dev"
Requires-Dist: hypothesis<=6.82.2,>=6.82; extra == "dev"
Requires-Dist: ruff<=0.0.28,>=0.0.28; extra == "dev"
Requires-Dist: coverage<=7.3.0,>=7.2.7; extra == "dev"
Requires-Dist: sphinx; extra == "dev"
Dynamic: author
Dynamic: home-page
Dynamic: license-file
Dynamic: maintainer
Dynamic: maintainer-email
Dynamic: requires-python
